svara/__init__.py
svara-0.0.1.dist-info/METADATA
svara-0.0.1.dist-info/WHEEL
svara-0.0.1.dist-info/top_level.txt
svara-0.0.1.dist-info/RECORD
