Metadata-Version: 2.4
Name: svara
Version: 0.0.1
Summary: Dummy lock package for svara
Author: AutoPublisher
